README.rst
setup.py
bin/celery_tasks_ctl
celery_tasks_ctl/__init__.py
celery_tasks_ctl/_version.py
celery_tasks_ctl/celery_tasks_ctl.py
celery_tasks_ctl.egg-info/PKG-INFO
celery_tasks_ctl.egg-info/SOURCES.txt
celery_tasks_ctl.egg-info/dependency_links.txt
celery_tasks_ctl.egg-info/requires.txt
celery_tasks_ctl.egg-info/top_level.txt
tests/__init__.py
tests/test_celery_tasks_ctl.py