Metadata-Version: 1.0
Name: celery-tasks-ctl
Version: 0.2.0
Summary: Celery Tasks Controller to list and revoke tasks
Home-page: UNKNOWN
Author: Brendan Maguire
Author-email: maguire.brendan@gmail.com
License: UNKNOWN
Platform: UNKNOWN
